shaclgen/__init__.py
shaclgen/__main__.py
shaclgen/constraint.py
shaclgen/schema.py
shaclgen/shaclgen.py
shaclgen/prefixes/namespaces.json
shaclgen-0.2.5.2.dist-info/METADATA
shaclgen-0.2.5.2.dist-info/WHEEL
shaclgen-0.2.5.2.dist-info/entry_points.txt
shaclgen-0.2.5.2.dist-info/top_level.txt
shaclgen-0.2.5.2.dist-info/RECORD
