Metadata-Version: 2.1
Name: shaclgen
Version: 0.2.5.2
Summary: Shacl graph generator
Home-page: https://github.com/uwlib-cams/shaclgen
Author: Alexis Keely
Author-email: alexiskeelie@gmail.com
License: MIT
Keywords: Linked Data,Semantic Web,Python,SHACL,Shapes,Schema,Validate
Platform: UNKNOWN
Classifier: Development Status :: 4 - Beta
Classifier: Programming Language :: Python :: 3
Requires-Dist: rdflib (>=4.2.2)
